ovos_stt_plugin_vosk/__init__.py
ovos_stt_plugin_vosk/version.py
ovos_stt_plugin_vosk-0.2.7.dist-info/licenses/LICENSE
ovos_stt_plugin_vosk-0.2.7.dist-info/METADATA
ovos_stt_plugin_vosk-0.2.7.dist-info/WHEEL
ovos_stt_plugin_vosk-0.2.7.dist-info/entry_points.txt
ovos_stt_plugin_vosk-0.2.7.dist-info/top_level.txt
ovos_stt_plugin_vosk-0.2.7.dist-info/zip-safe
ovos_stt_plugin_vosk-0.2.7.dist-info/RECORD
