Metadata-Version: 2.4
Name: ovos-stt-plugin-vosk
Version: 0.2.7
Summary: A vosk stt plugin for OpenVoiceOS
Home-page: https://github.com/OpenVoiceOS/ovos-stt-plugin-vosk
Author: JarbasAi
Author-email: jarbasai@mailfence.com
License: Apache-2.0
Keywords: mycroft ovos plugin stt
Classifier: Development Status :: 3 - Alpha
Classifier: Intended Audience :: Developers
Classifier: License :: OSI Approved :: Apache Software License
License-File: LICENSE
Requires-Dist: vosk
Requires-Dist: ovos-plugin-manager<3.0.0,>=2.1.1
Requires-Dist: ovos-utils<1.0.0,>=0.8.4
Dynamic: author
Dynamic: author-email
Dynamic: classifier
Dynamic: home-page
Dynamic: keywords
Dynamic: license
Dynamic: license-file
Dynamic: requires-dist
Dynamic: summary
